bophono/PhonStateCAT.py
bophono/PhonStateKVP.py
bophono/PhonStateLKT.py
bophono/PhonStateMST.py
bophono/UnicodeToApi.py
bophono/__init__.py
bophono/apitochinese.py
bophono/sdtrie.py
bophono/data/README.md
bophono/data/ends.csv
bophono/data/exceptions-kvp.csv
bophono/data/exceptions-lkt.csv
bophono/data/exceptions.csv
bophono/data/roots.csv
bophono/data/chinese/chinese_trad.csv
bophono/data/chinese/exception.csv
bophono/data/chinese/zhuyin.csv
bophono-0.2.0.dist-info/LICENSE
bophono-0.2.0.dist-info/METADATA
bophono-0.2.0.dist-info/WHEEL
bophono-0.2.0.dist-info/top_level.txt
bophono-0.2.0.dist-info/RECORD
