Metadata-Version: 2.1
Name: bophono
Version: 0.2.0
Summary: Python utils for Tibetan phonetics in different dialects
Home-page: https://github.com/Esukhia/bophono
Author: Esukhia development team
Author-email: roux.elie@gmail.com
License: MIT
Project-URL: Source, https://github.com/Esukhia/bophono
Project-URL: Tracker, https://github.com/Esukhia/bophono/issues
Keywords: phonetics IPA tibetan
Classifier: Development Status :: 3 - Alpha
Classifier: Topic :: Text Processing :: Linguistic
Classifier: Programming Language :: Python :: 3
Classifier: Operating System :: OS Independent
Classifier: Intended Audience :: Developers
Classifier: Intended Audience :: Science/Research
Classifier: License :: OSI Approved :: MIT License
Classifier: Natural Language :: Tibetan
Requires-Python: >=3
License-File: LICENSE
